Workbook

Sheet Parámetros
A1: PARÁMETROS DEL SISTEMA DE CÁLCULO — NORMATIVA SIGESP ERP (Octubre 2026)
A3: 1. TARIFAS DE VENTA POR ZONA (USD/hora)
A4: Zona | B4: Tarifa Presencial ($/h) | C4: Tarifa Online ($/h) | E4: Estados / cobertura
A5: Oriental | B5: 115 | C5: 55 | E5: Nueva Esparta, Anzoátegui, Amazonas, Sucre, Monagas, Bolívar, Apure
A6: Central | B6: 90 | C6: 55 | E6: Caracas, Miranda, Aragua, Carabobo, Guárico
A7: Centroccidental | B7: 70 | C7: 55 | E7: Lara (Barquisimeto y Cabudare), Yaracuy, Portuguesa, Cojedes
A8: Occidental | B8: 105 | C8: 55 | E8: Táchira, Mérida, Falcón, Trujillo, Zulia
A10: 2. COSTOS DE CONSULTORÍA (USD/hora)
A11: Zona | B11: Costo Presencial ($/h) | C11: Costo Online ($/h) | E11: Nota
A12: Oriental | B12: 30 | C12: 18 | E12: Tarifa plana de consultoría
A13: Central | B13: 30 | C13: 18 | E13: Tarifa plana de consultoría
A14: Centroccidental | B14: 20 | C14: 18 | E14: Detalle por estado: Yaracuy 20; Acarigua 18; Guanare/Cojedes 22; Barquisimeto/Cabudare 12; Quíbor/Morán 14 (se usó 20 como promedio).
A15: Occidental | B15: 30 | C15: 18 | E15: Tarifa plana de consultoría
A16: El costo de hora online no lo fija la normativa original; aquí se propone 18 $/h (60% del presencial). Ajústelo en la columna C.
A17: 3. OTROS PARÁMETROS
A18: % Impuesto sobre la renta (ISLR) | B18: 0.01 | E18: Regla 1.3.1.4 — 1% del monto recibido
A19: % Impuesto municipal (actividades económicas) | B19: 0.03 | E19: Regla 1.3.1.4.1.3.1 — 3%
A20: % Gobernación | B20: 0.01 | E20: Regla 1.3.1.4.1.3.1 — 1%
A21: % Responsabilidad social | B21: 0.03 | E21: Regla de registro — 3% del monto recibido
A22: % Fianzas / retención sustitutiva | B22: 0.1 | E22: 10% cuando no se acepta retención
A23: % Costos y gastos indirectos (sobre ingreso) | B23: 0.35 | E23: Sugerido; la normativa lo estima por proyecto
A24: % Utilidad objetivo mínima | B24: 0.3 | E24: Umbral de control de rentabilidad
A25: Índice de inflación acumulado (base Oct-2026 = 1,00) | B25: 1 | E25: Precio_mes = Precio_base × índice. Actualícelo con la variación BCV.
E28: Tramos de usuarios (lista auxiliar)
E29: 30
E30: 50
E31: 100
E32: 150

Sheet Detalle30
A1: DETALLE DE ACTIVIDADES — IMPLANTACIÓN HASTA 30 USUARIOS (editable)
A2: Al modificar estas horas, la hoja 'Horas' y la 'MatrizPrecios' se recalculan solas.
A3: Horas por actividad y alcance
A4: Actividad | B4: Tipo | C4: Admon sin nómina (A1) | D4: Admon con nómina (A2) | E4: Admon + Comercial (A3) | F4: Admon + Com. + Producción (A4)
A5: Creación del comité de implantación | B5: Presencial | C5: 2 | D5: 2 | E5: 2 | F5: 2
A6: Presentación del sistema a todos los usuarios | B6: Presencial | C6: 3 | D6: 3 | E6: 3 | F6: 3
A7: Levantamiento presencial de la información | B7: Presencial | C7: 12 | D7: 18 | E7: 25 | F7: 40
A8: Certificación de los datos migrados | B8: Presencial | C8: 12 | D8: 18 | E8: 24 | F8: 32
A9: Capacitación del personal para carga de datos | B9: Presencial | C9: 12 | D9: 18 | E9: 22 | F9: 30
A10: Capacitación simulada del sistema | B10: Presencial | C10: 18 | D10: 18 | E10: 24 | F10: 36
A11: Capacitación en vivo | B11: Presencial | C11: 60 | D11: 110 | E11: 140 | F11: 180
A12: SUBTOTAL PRESENCIAL | C12: =SUM(C5:C11) -> 119 | D12: =SUM(D5:D11) -> 187 | E12: =SUM(E5:E11) -> 240 | F12: =SUM(F5:F11) -> 323
A13: Configuración del sistema y datos básicos | B13: Online | C13: 35 | D13: 60 | E13: 80 | F13: 120
A14: Migración de los datos | B14: Online | C14: 35 | D14: 60 | E14: 80 | F14: 120
A15: Cambios solicitados en reportes o procesos | B15: Online | C15: 45 | D15: 75 | E15: 100 | F15: 160
A16: Mantenimiento 3 meses (incluido en la venta) | B16: Online | C16: 60 | D16: 80 | E16: 100 | F16: 130
A17: SUBTOTAL ONLINE | C17: =SUM(C13:C16) -> 175 | D17: =SUM(D13:D16) -> 275 | E17: =SUM(E13:E16) -> 360 | F17: =SUM(F13:F16) -> 530
A18: TOTAL HORAS | C18: =C12+C17 -> 294 | D18: =D12+D17 -> 462 | E18: =E12+E17 -> 600 | F18: =F12+F17 -> 853
A20: Clasificación aplicada (implícita en la normativa): Presencial = comité, presentación, levantamiento, certificación y capacitaciones. Online = configuración, migración, cambios y mantenimiento.

Sheet Horas
A1: HORAS ESTIMADAS POR TRAMO DE USUARIOS Y ALCANCE
A3: Tramo usuarios | B3: Alcance | C3: Horas Presenciales | D3: Horas Online | E3: Total
A4: 30 | B4: Admin sin nómina | C4: =Detalle30!C12 -> 119 | D4: =Detalle30!C17 -> 175 | E4: =C4+D4 -> 294
A5: 30 | B5: Admin con nómina | C5: =Detalle30!D12 -> 187 | D5: =Detalle30!D17 -> 275 | E5: =C5+D5 -> 462
A6: 30 | B6: Admin + Comercial | C6: =Detalle30!E12 -> 240 | D6: =Detalle30!E17 -> 360 | E6: =C6+D6 -> 600
A7: 30 | B7: Admin + Comercial + Producción | C7: =Detalle30!F12 -> 323 | D7: =Detalle30!F17 -> 530 | E7: =C7+D7 -> 853
A8: 50 | B8: Admin sin nómina | C8: 130 | D8: 192 | E8: =C8+D8 -> 322
A9: 50 | B9: Admin con nómina | C9: 206 | D9: 300 | E9: =C9+D9 -> 506
A10: 50 | B10: Admin + Comercial | C10: 260 | D10: 400 | E10: =C10+D10 -> 660
A11: 50 | B11: Admin + Comercial + Producción | C11: 350 | D11: 580 | E11: =C11+D11 -> 930
A12: 100 | B12: Admin sin nómina | C12: 143 | D12: 210 | E12: =C12+D12 -> 353
A13: 100 | B13: Admin con nómina | C13: 225 | D13: 330 | E13: =C13+D13 -> 555
A14: 100 | B14: Admin + Comercial | C14: 285 | D14: 440 | E14: =C14+D14 -> 725
A15: 100 | B15: Admin + Comercial + Producción | C15: 385 | D15: 640 | E15: =C15+D15 -> 1025
A16: 150 | B16: Admin sin nómina | C16: 160 | D16: 230 | E16: =C16+D16 -> 390
A17: 150 | B17: Admin con nómina | C17: 250 | D17: 360 | E17: =C17+D17 -> 610
A18: 150 | B18: Admin + Comercial | C18: 300 | D18: 480 | E18: =C18+D18 -> 780
A19: 150 | B19: Admin + Comercial + Producción | C19: 415 | D19: 700 | E19: =C19+D19 -> 1115
A21: Para tramos mayores a 30 usuarios la normativa solo ofrece totales (no el detalle por actividad).

Sheet MatrizPrecios
A1: MATRIZ DE PRECIOS DE IMPLANTACIÓN (calculada automáticamente)
A2: Precio = Horas Presenciales × Tarifa_zona + Horas Online × Tarifa_online. Cambie tarifas en 'Parámetros'.
A3: Tramo | B3: Alcance | C3: Horas Pres. | D3: Horas Online | E3: Oriental | F3: Central | G3: Centroccidental | H3: Occidental
A4: 30 | B4: Admin sin nómina | C4: =SUMIFS(Horas!$C$4:$C$19,Horas!$A$4:$A$19,$A4,Horas!$B$4:$B$19,$B4) -> 119 | D4: =SUMIFS(Horas!$D$4:$D$19,Horas!$A$4:$A$19,$A4,Horas!$B$4:$B$19,$B4) -> 175 | E4: =$C4*VLOOKUP(E$3,Parámetros!$A$5:$C$8,2,FALSE)+$D4*VLOOKUP(E$3,Parámetros!$A$5:$C$8,3,FALSE) -> 23310 | F4: =$C4*VLOOKUP(F$3,Parámetros!$A$5:$C$8,2,FALSE)+$D4*VLOOKUP(F$3,Parámetros!$A$5:$C$8,3,FALSE) -> 20335 | G4: =$C4*VLOOKUP(G$3,Parámetros!$A$5:$C$8,2,FALSE)+$D4*VLOOKUP(G$3,Parámetros!$A$5:$C$8,3,FALSE) -> 17955 | H4: =$C4*VLOOKUP(H$3,Parámetros!$A$5:$C$8,2,FALSE)+$D4*VLOOKUP(H$3,Parámetros!$A$5:$C$8,3,FALSE) -> 22120
A5: 30 | B5: Admin con nómina | C5: =SUMIFS(Horas!$C$4:$C$19,Horas!$A$4:$A$19,$A5,Horas!$B$4:$B$19,$B5) -> 187 | D5: =SUMIFS(Horas!$D$4:$D$19,Horas!$A$4:$A$19,$A5,Horas!$B$4:$B$19,$B5) -> 275 | E5: =$C5*VLOOKUP(E$3,Parámetros!$A$5:$C$8,2,FALSE)+$D5*VLOOKUP(E$3,Parámetros!$A$5:$C$8,3,FALSE) -> 36630 | F5: =$C5*VLOOKUP(F$3,Parámetros!$A$5:$C$8,2,FALSE)+$D5*VLOOKUP(F$3,Parámetros!$A$5:$C$8,3,FALSE) -> 31955 | G5: =$C5*VLOOKUP(G$3,Parámetros!$A$5:$C$8,2,FALSE)+$D5*VLOOKUP(G$3,Parámetros!$A$5:$C$8,3,FALSE) -> 28215 | H5: =$C5*VLOOKUP(H$3,Parámetros!$A$5:$C$8,2,FALSE)+$D5*VLOOKUP(H$3,Parámetros!$A$5:$C$8,3,FALSE) -> 34760
A6: 30 | B6: Admin + Comercial | C6: =SUMIFS(Horas!$C$4:$C$19,Horas!$A$4:$A$19,$A6,Horas!$B$4:$B$19,$B6) -> 240 | D6: =SUMIFS(Horas!$D$4:$D$19,Horas!$A$4:$A$19,$A6,Horas!$B$4:$B$19,$B6) -> 360 | E6: =$C6*VLOOKUP(E$3,Parámetros!$A$5:$C$8,2,FALSE)+$D6*VLOOKUP(E$3,Parámetros!$A$5:$C$8,3,FALSE) -> 47400 | F6: =$C6*VLOOKUP(F$3,Parámetros!$A$5:$C$8,2,FALSE)+$D6*VLOOKUP(F$3,Parámetros!$A$5:$C$8,3,FALSE) -> 41400 | G6: =$C6*VLOOKUP(G$3,Parámetros!$A$5:$C$8,2,FALSE)+$D6*VLOOKUP(G$3,Parámetros!$A$5:$C$8,3,FALSE) -> 36600 | H6: =$C6*VLOOKUP(H$3,Parámetros!$A$5:$C$8,2,FALSE)+$D6*VLOOKUP(H$3,Parámetros!$A$5:$C$8,3,FALSE) -> 45000
A7: 30 | B7: Admin + Comercial + Producción | C7: =SUMIFS(Horas!$C$4:$C$19,Horas!$A$4:$A$19,$A7,Horas!$B$4:$B$19,$B7) -> 323 | D7: =SUMIFS(Horas!$D$4:$D$19,Horas!$A$4:$A$19,$A7,Horas!$B$4:$B$19,$B7) -> 530 | E7: =$C7*VLOOKUP(E$3,Parámetros!$A$5:$C$8,2,FALSE)+$D7*VLOOKUP(E$3,Parámetros!$A$5:$C$8,3,FALSE) -> 66295 | F7: =$C7*VLOOKUP(F$3,Parámetros!$A$5:$C$8,2,FALSE)+$D7*VLOOKUP(F$3,Parámetros!$A$5:$C$8,3,FALSE) -> 58220 | G7: =$C7*VLOOKUP(G$3,Parámetros!$A$5:$C$8,2,FALSE)+$D7*VLOOKUP(G$3,Parámetros!$A$5:$C$8,3,FALSE) -> 51760 | H7: =$C7*VLOOKUP(H$3,Parámetros!$A$5:$C$8,2,FALSE)+$D7*VLOOKUP(H$3,Parámetros!$A$5:$C$8,3,FALSE) -> 63065
A8: 50 | B8: Admin sin nómina | C8: =SUMIFS(Horas!$C$4:$C$19,Horas!$A$4:$A$19,$A8,Horas!$B$4:$B$19,$B8) -> 130 | D8: =SUMIFS(Horas!$D$4:$D$19,Horas!$A$4:$A$19,$A8,Horas!$B$4:$B$19,$B8) -> 192 | E8: =$C8*VLOOKUP(E$3,Parámetros!$A$5:$C$8,2,FALSE)+$D8*VLOOKUP(E$3,Parámetros!$A$5:$C$8,3,FALSE) -> 25510 | F8: =$C8*VLOOKUP(F$3,Parámetros!$A$5:$C$8,2,FALSE)+$D8*VLOOKUP(F$3,Parámetros!$A$5:$C$8,3,FALSE) -> 22260 | G8: =$C8*VLOOKUP(G$3,Parámetros!$A$5:$C$8,2,FALSE)+$D8*VLOOKUP(G$3,Parámetros!$A$5:$C$8,3,FALSE) -> 19660 | H8: =$C8*VLOOKUP(H$3,Parámetros!$A$5:$C$8,2,FALSE)+$D8*VLOOKUP(H$3,Parámetros!$A$5:$C$8,3,FALSE) -> 24210
A9: 50 | B9: Admin con nómina | C9: =SUMIFS(Horas!$C$4:$C$19,Horas!$A$4:$A$19,$A9,Horas!$B$4:$B$19,$B9) -> 206 | D9: =SUMIFS(Horas!$D$4:$D$19,Horas!$A$4:$A$19,$A9,Horas!$B$4:$B$19,$B9) -> 300 | E9: =$C9*VLOOKUP(E$3,Parámetros!$A$5:$C$8,2,FALSE)+$D9*VLOOKUP(E$3,Parámetros!$A$5:$C$8,3,FALSE) -> 40190 | F9: =$C9*VLOOKUP(F$3,Parámetros!$A$5:$C$8,2,FALSE)+$D9*VLOOKUP(F$3,Parámetros!$A$5:$C$8,3,FALSE) -> 35040 | G9: =$C9*VLOOKUP(G$3,Parámetros!$A$5:$C$8,2,FALSE)+$D9*VLOOKUP(G$3,Parámetros!$A$5:$C$8,3,FALSE) -> 30920 | H9: =$C9*VLOOKUP(H$3,Parámetros!$A$5:$C$8,2,FALSE)+$D9*VLOOKUP(H$3,Parámetros!$A$5:$C$8,3,FALSE) -> 38130
A10: 50 | B10: Admin + Comercial | C10: =SUMIFS(Horas!$C$4:$C$19,Horas!$A$4:$A$19,$A10,Horas!$B$4:$B$19,$B10) -> 260 | D10: =SUMIFS(Horas!$D$4:$D$19,Horas!$A$4:$A$19,$A10,Horas!$B$4:$B$19,$B10) -> 400 | E10: =$C10*VLOOKUP(E$3,Parámetros!$A$5:$C$8,2,FALSE)+$D10*VLOOKUP(E$3,Parámetros!$A$5:$C$8,3,FALSE) -> 51900 | F10: =$C10*VLOOKUP(F$3,Parámetros!$A$5:$C$8,2,FALSE)+$D10*VLOOKUP(F$3,Parámetros!$A$5:$C$8,3,FALSE) -> 45400 | G10: =$C10*VLOOKUP(G$3,Parámetros!$A$5:$C$8,2,FALSE)+$D10*VLOOKUP(G$3,Parámetros!$A$5:$C$8,3,FALSE) -> 40200 | H10: =$C10*VLOOKUP(H$3,Parámetros!$A$5:$C$8,2,FALSE)+$D10*VLOOKUP(H$3,Parámetros!$A$5:$C$8,3,FALSE) -> 49300
A11: 50 | B11: Admin + Comercial + Producción | C11: =SUMIFS(Horas!$C$4:$C$19,Horas!$A$4:$A$19,$A11,Horas!$B$4:$B$19,$B11) -> 350 | D11: =SUMIFS(Horas!$D$4:$D$19,Horas!$A$4:$A$19,$A11,Horas!$B$4:$B$19,$B11) -> 580 | E11: =$C11*VLOOKUP(E$3,Parámetros!$A$5:$C$8,2,FALSE)+$D11*VLOOKUP(E$3,Parámetros!$A$5:$C$8,3,FALSE) -> 72150 | F11: =$C11*VLOOKUP(F$3,Parámetros!$A$5:$C$8,2,FALSE)+$D11*VLOOKUP(F$3,Parámetros!$A$5:$C$8,3,FALSE) -> 63400 | G11: =$C11*VLOOKUP(G$3,Parámetros!$A$5:$C$8,2,FALSE)+$D11*VLOOKUP(G$3,Parámetros!$A$5:$C$8,3,FALSE) -> 56400 | H11: =$C11*VLOOKUP(H$3,Parámetros!$A$5:$C$8,2,FALSE)+$D11*VLOOKUP(H$3,Parámetros!$A$5:$C$8,3,FALSE) -> 68650
A12: 100 | B12: Admin sin nómina | C12: =SUMIFS(Horas!$C$4:$C$19,Horas!$A$4:$A$19,$A12,Horas!$B$4:$B$19,$B12) -> 143 | D12: =SUMIFS(Horas!$D$4:$D$19,Horas!$A$4:$A$19,$A12,Horas!$B$4:$B$19,$B12) -> 210 | E12: =$C12*VLOOKUP(E$3,Parámetros!$A$5:$C$8,2,FALSE)+$D12*VLOOKUP(E$3,Parámetros!$A$5:$C$8,3,FALSE) -> 27995 | F12: =$C12*VLOOKUP(F$3,Parámetros!$A$5:$C$8,2,FALSE)+$D12*VLOOKUP(F$3,Parámetros!$A$5:$C$8,3,FALSE) -> 24420 | G12: =$C12*VLOOKUP(G$3,Parámetros!$A$5:$C$8,2,FALSE)+$D12*VLOOKUP(G$3,Parámetros!$A$5:$C$8,3,FALSE) -> 21560 | H12: =$C12*VLOOKUP(H$3,Parámetros!$A$5:$C$8,2,FALSE)+$D12*VLOOKUP(H$3,Parámetros!$A$5:$C$8,3,FALSE) -> 26565
A13: 100 | B13: Admin con nómina | C13: =SUMIFS(Horas!$C$4:$C$19,Horas!$A$4:$A$19,$A13,Horas!$B$4:$B$19,$B13) -> 225 | D13: =SUMIFS(Horas!$D$4:$D$19,Horas!$A$4:$A$19,$A13,Horas!$B$4:$B$19,$B13) -> 330 | E13: =$C13*VLOOKUP(E$3,Parámetros!$A$5:$C$8,2,FALSE)+$D13*VLOOKUP(E$3,Parámetros!$A$5:$C$8,3,FALSE) -> 44025 | F13: =$C13*VLOOKUP(F$3,Parámetros!$A$5:$C$8,2,FALSE)+$D13*VLOOKUP(F$3,Parámetros!$A$5:$C$8,3,FALSE) -> 38400 | G13: =$C13*VLOOKUP(G$3,Parámetros!$A$5:$C$8,2,FALSE)+$D13*VLOOKUP(G$3,Parámetros!$A$5:$C$8,3,FALSE) -> 33900 | H13: =$C13*VLOOKUP(H$3,Parámetros!$A$5:$C$8,2,FALSE)+$D13*VLOOKUP(H$3,Parámetros!$A$5:$C$8,3,FALSE) -> 41775
A14: 100 | B14: Admin + Comercial | C14: =SUMIFS(Horas!$C$4:$C$19,Horas!$A$4:$A$19,$A14,Horas!$B$4:$B$19,$B14) -> 285 | D14: =SUMIFS(Horas!$D$4:$D$19,Horas!$A$4:$A$19,$A14,Horas!$B$4:$B$19,$B14) -> 440 | E14: =$C14*VLOOKUP(E$3,Parámetros!$A$5:$C$8,2,FALSE)+$D14*VLOOKUP(E$3,Parámetros!$A$5:$C$8,3,FALSE) -> 56975 | F14: =$C14*VLOOKUP(F$3,Parámetros!$A$5:$C$8,2,FALSE)+$D14*VLOOKUP(F$3,Parámetros!$A$5:$C$8,3,FALSE) -> 49850 | G14: =$C14*VLOOKUP(G$3,Parámetros!$A$5:$C$8,2,FALSE)+$D14*VLOOKUP(G$3,Parámetros!$A$5:$C$8,3,FALSE) -> 44150 | H14: =$C14*VLOOKUP(H$3,Parámetros!$A$5:$C$8,2,FALSE)+$D14*VLOOKUP(H$3,Parámetros!$A$5:$C$8,3,FALSE) -> 54125
A15: 100 | B15: Admin + Comercial + Producción | C15: =SUMIFS(Horas!$C$4:$C$19,Horas!$A$4:$A$19,$A15,Horas!$B$4:$B$19,$B15) -> 385 | D15: =SUMIFS(Horas!$D$4:$D$19,Horas!$A$4:$A$19,$A15,Horas!$B$4:$B$19,$B15) -> 640 | E15: =$C15*VLOOKUP(E$3,Parámetros!$A$5:$C$8,2,FALSE)+$D15*VLOOKUP(E$3,Parámetros!$A$5:$C$8,3,FALSE) -> 79475 | F15: =$C15*VLOOKUP(F$3,Parámetros!$A$5:$C$8,2,FALSE)+$D15*VLOOKUP(F$3,Parámetros!$A$5:$C$8,3,FALSE) -> 69850 | G15: =$C15*VLOOKUP(G$3,Parámetros!$A$5:$C$8,2,FALSE)+$D15*VLOOKUP(G$3,Parámetros!$A$5:$C$8,3,FALSE) -> 62150 | H15: =$C15*VLOOKUP(H$3,Parámetros!$A$5:$C$8,2,FALSE)+$D15*VLOOKUP(H$3,Parámetros!$A$5:$C$8,3,FALSE) -> 75625
... A19: 150 | B19: Admin + Comercial + Producción | C19: =SUMIFS(Horas!$C$4:$C$19,Horas!$A$4:$A$19,$A19,Horas!$B$4:$B$19,$B19) -> 415 | D19: =SUMIFS(Horas!$D$4:$D$19,Horas!$A$4:$A$19,$A19,Horas!$B$4:$B$19,$B19) -> 700 | E19: =$C19*VLOOKUP(E$3,Parámetros!$A$5:$C$8,2,FALSE)+$D19*VLOOKUP(E$3,Parámetros!$A$5:$C$8,3,FALSE) -> 86225 | F19: =$C19*VLOOKUP(F$3,Parámetros!$A$5:$C$8,2,FALSE)+$D19*VLOOKUP(F$3,Parámetros!$A$5:$C$8,3,FALSE) -> 75850 | G19: =$C19*VLOOKUP(G$3,Parámetros!$A$5:$C$8,2,FALSE)+$D19*VLOOKUP(G$3,Parámetros!$A$5:$C$8,3,FALSE) -> 67550 | H19: =$C19*VLOOKUP(H$3,Parámetros!$A$5:$C$8,2,FALSE)+$D19*VLOOKUP(H$3,Parámetros!$A$5:$C$8,3,FALSE) -> 82075
A20: La fila '30 – Admin + Comercial + Producción / Centroccidental' ya sale corregida (51.760,00) frente al error del documento (58.221,00).

Sheet Cotizador
A1: COTIZADOR DE IMPLANTACIÓN SIGESP ERP
A3: Zona: | B3: Oriental
A4: Tramo de usuarios: | B4: 30
A5: N° de usuarios (informativo): | B5: 30
A6: Descuento (%): | B6: 0
A7: Cliente / proyecto:
A9: DETALLE POR ALCANCE — Alcance | B9: Incluir | C9: Horas Pres. | D9: Horas Online | E9: Tarifa Pres. ($/h) | F9: Precio Pres. ($) | G9: Precio Online ($) | H9: Subtotal ($)
A10: Admin sin nómina | B10: Sí | C10: =SUMIFS(Horas!$C$4:$C$19,Horas!$A$4:$A$19,$B$4,Horas!$B$4:$B$19,$A10) -> 119 | D10: =SUMIFS(Horas!$D$4:$D$19,Horas!$A$4:$A$19,$B$4,Horas!$B$4:$B$19,$A10) -> 175 | E10: =VLOOKUP($B$3,Parámetros!$A$5:$C$8,2,FALSE) -> 115 | F10: =C10*E10 -> 13685 | G10: =D10*VLOOKUP($B$3,Parámetros!$A$5:$C$8,3,FALSE) -> 9625 | H10: =IF($B10="Sí",F10+G10,0) -> 23310
A11: Admin con nómina | B11: Sí | C11: =SUMIFS(Horas!$C$4:$C$19,Horas!$A$4:$A$19,$B$4,Horas!$B$4:$B$19,$A11) -> 187 | D11: =SUMIFS(Horas!$D$4:$D$19,Horas!$A$4:$A$19,$B$4,Horas!$B$4:$B$19,$A11) -> 275 | E11: =VLOOKUP($B$3,Parámetros!$A$5:$C$8,2,FALSE) -> 115 | F11: =C11*E11 -> 21505 | G11: =D11*VLOOKUP($B$3,Parámetros!$A$5:$C$8,3,FALSE) -> 15125 | H11: =IF($B11="Sí",F11+G11,0) -> 36630
A12: Admin + Comercial | B12: Sí | C12: =SUMIFS(Horas!$C$4:$C$19,Horas!$A$4:$A$19,$B$4,Horas!$B$4:$B$19,$A12) -> 240 | D12: =SUMIFS(Horas!$D$4:$D$19,Horas!$A$4:$A$19,$B$4,Horas!$B$4:$B$19,$A12) -> 360 | E12: =VLOOKUP($B$3,Parámetros!$A$5:$C$8,2,FALSE) -> 115 | F12: =C12*E12 -> 27600 | G12: =D12*VLOOKUP($B$3,Parámetros!$A$5:$C$8,3,FALSE) -> 19800 | H12: =IF($B12="Sí",F12+G12,0) -> 47400
A13: Admin + Comercial + Producción | B13: Sí | C13: =SUMIFS(Horas!$C$4:$C$19,Horas!$A$4:$A$19,$B$4,Horas!$B$4:$B$19,$A13) -> 323 | D13: =SUMIFS(Horas!$D$4:$D$19,Horas!$A$4:$A$19,$B$4,Horas!$B$4:$B$19,$A13) -> 530 | E13: =VLOOKUP($B$3,Parámetros!$A$5:$C$8,2,FALSE) -> 115 | F13: =C13*E13 -> 37145 | G13: =D13*VLOOKUP($B$3,Parámetros!$A$5:$C$8,3,FALSE) -> 29150 | H13: =IF($B13="Sí",F13+G13,0) -> 66295
A15: TOTALES (solo alcances incluidos) | C15: =SUMIF($B$10:$B$13,"Sí",C10:C13) -> 869 | D15: =SUMIF($B$10:$B$13,"Sí",D10:D13) -> 1340 | F15: =SUMIF($B$10:$B$13,"Sí",F10:F13) -> 99935 | G15: =SUMIF($B$10:$B$13,"Sí",G10:G13) -> 73700 | H15: =SUM(H10:H13) -> 173635
A17: Subtotal cotización ($) | C17: =H15 -> 173635
A18: Descuento aplicado ($) | C18: =H15*$B$6 -> 0
A19: TOTAL A COTIZAR ($) | C19: =H15-C18 -> 173635
A21: Análisis de costos y rentabilidad
A22: Costo hora consultor presencial ($/h) | C22: =VLOOKUP($B$3,Parámetros!$A$12:$C$15,2,FALSE) -> 30
A23: Costo hora online ($/h) | C23: =VLOOKUP($B$3,Parámetros!$A$12:$C$15,3,FALSE) -> 18
A24: Costo directo de consultoría ($) | C24: =C15*C22+D15*C23 -> 50190
A25: Otros costos directos (% del ingreso) | C25: =Parámetros!$B$18+Parámetros!$B$19+Parámetros!$B$20+Parámetros!$B$21 -> 0.08
A26: Otros costos directos ($) | C26: =C19*C25 -> 13890.8
A27: Costos indirectos ($) | C27: =C19*Parámetros!$B$23 -> 60772.25
A28: TOTAL COSTOS ($) | C28: =C24+C26+C27 -> 124853.05
A29: Utilidad estimada ($) | C29: =C19-C28 -> 48781.95
A30: Margen (%) | C30: =IF(C19=0,0,C29/C19) -> 0.28094537
A31: Objetivo mínimo (%) | C31: =Parámetros!$B$24 -> 0.3
A32: Control de rentabilidad | C32: =IF(C30>=C31,"✔ Cumple el objetivo","✖ Bajo el objetivo") -> ✖ Bajo el objetivo

Sheet Mantenimiento
A1: SERVICIOS DE MANTENIMIENTO ONLINE
A3: TARIFARIO — Rango de usuarios | B3: Mensual | C3: Trimestral | D3: Semestral | E3: Anual
A4: Hasta 30 | B4: 400 | C4: =B4*3 -> 1200 | D4: =B4*6 -> 2400 | E4: =B4*12 -> 4800
A5: 31 a 60 | B5: 700 | C5: =B5*3 -> 2100 | D5: =B5*6 -> 4200 | E5: =B5*12 -> 8400
A6: 61 a 120 | B6: 1000 | C6: =B6*3 -> 3000 | D6: =B6*6 -> 6000 | E6: =B6*12 -> 12000
A7: Más de 120 | B7: 1500 | C7: =B7*3 -> 4500 | D7: =B7*6 -> 9000 | E7: =B7*12 -> 18000
A9: Simulador
A10: Rango de usuarios: | B10: Hasta 30
A11: Plan: | B11: Mensual
A12: Precio del plan ($): | B12: =INDEX($B$4:$E$7,MATCH($B$10,$A$4:$A$7,0),MATCH($B$11,$B$3:$E$3,0)) -> 400
A13: Valor de 3 meses incluidos en la implantación ($): | B13: =3*INDEX($B$4:$B$7,MATCH($B$10,$A$4:$A$7,0)) -> 1200
A14: Horas equivalentes (tarifa online 55 $/h): | B14: =B13/55 -> 21.818182
A16: La normativa valora los 3 meses gratuitos como 60–130 horas (3.300–7.150 $), distinto de la tarifa de mantenimiento (1.200–4.500 $). Este simulador unifica el criterio por tarifa.

Sheet Costos
A1: DISTRIBUCIÓN DE COSTOS, GASTOS Y RENTABILIDAD
A3: Entrada
A4: Ingreso neto cobrado ($) | C4: 32000
A5: Horas presenciales facturadas | C5: 187
A6: Horas online facturadas | C6: 275
A7: Costo hora presencial ($/h) | C7: 30
A8: Costo hora online ($/h) | C8: 18
A9: Total horas | C9: =C5+C6 -> 462
A11: COSTOS DIRECTOS — Concepto | B11: % del ingreso | C11: Monto ($) | D11: Nota
A12: Consultoría presencial | C12: =C5*C7 -> 5610 | D12: horas × costo
A13: Consultoría online | C13: =C6*C8 -> 4950 | D13: horas × costo
A14: Impuesto sobre la renta (ISLR) | B14: =Parámetros!$B$18 -> 0.01 | C14: =$C$4*B14 -> 320 | D14: 1% del monto
A15: Impuesto municipal (act. económicas) | B15: =Parámetros!$B$19 -> 0.03 | C15: =$C$4*B15 -> 960 | D15: 3% del monto
A16: Gobernación | B16: =Parámetros!$B$20 -> 0.01 | C16: =$C$4*B16 -> 320 | D16: 1% del monto
A17: Responsabilidad social | B17: =Parámetros!$B$21 -> 0.03 | C17: =$C$4*B17 -> 960 | D17: 3% del monto
A18: Fianzas / retención | B18: =Parámetros!$B$22 -> 0.1 | C18: =$C$4*B18 -> 3200 | D18: si no se acepta retención
A19: Otros directos | B19: 0 | C19: =$C$4*B19 -> 0 | D19: ajustable
A20: TOTAL COSTOS DIRECTOS | C20: =SUM(C12:C19) -> 16320
A22: COSTOS INDIRECTOS — Concepto | B22: % del ingreso | C22: Monto ($) | D22: Nota
A23: Honorarios a directivos | B23: 0.25 | C23: =$C$4*B23 -> 8000 | D23: propuesto como % fijo
A24: Honorarios administración y desarrollo | B24: 0.1 | C24: =$C$4*B24 -> 3200 | D24: de la venta neta
A25: Otros gastos de servicios / personal | B25: 0.025 | C25: =$C$4*B25 -> 800 | D25: distribución mensual
A26: Impuestos actividades económicas SIGESP | B26: 0.03 | C26: =$C$4*B26 -> 960 | D26: 3% del monto
A27: Servicios generales (agua, luz, tel.) | B27: 0.015 | C27: =$C$4*B27 -> 480 | D27: 1,5% del bruto
A28: Servidores e IA | B28: 0.02 | C28: =$C$4*B28 -> 640 | D28: estimado
A29: Reposición de mobiliario y equipos | B29: 0.02 | C29: =$C$4*B29 -> 640 | D29: estimado
A30: TOTAL COSTOS INDIRECTOS | C30: =SUM(C23:C29) -> 14720
A32: TOTAL COSTOS | C32: =C20+C30 -> 31040
A33: UTILIDAD ESTIMADA | C33: =C4-C32 -> 960
A34: MARGEN | C34: =IF(C4=0,0,C33/C4) -> 0.03
A37: VERIFICACIÓN DE EJEMPLOS — Concepto | B37: Documento | C37: Correcto | D37: Observación
A38: Ej. 1 — Otros costos directos de venta | B38: 2200 | C38: 2600 | D38: Los componentes (300+200+600+1.500) suman 2.600, no 2.200.
A39: Ej. 2 — Costos indirectos | B39: 10200 | C39: 11200 | D39: Los componentes suman 11.200. Con 11.200 el costo total es 18.300 y la utilidad cae a ~100.
A40: Ej. 1 — Responsabilidad social (3%) | B40: 600 | C40: 960 | D40: 3% de 32.000 = 960.
A41: Ej. 2 — ISLR (1%) | B41: 700 | C41: 184 | D41: 1% de 18.400 = 184; el documento usa 3,8%.

Sheet Instrucciones
A1: INSTRUCCIONES DE USO DEL SISTEMA DE CÁLCULO
A3: 1) Todo el libro está enlazado por fórmulas. Las celdas amarillas son entradas editables; las demás se calculan.
A5: 2) Hoja 'Parámetros': tarifas por zona, costos de consultoría, porcentajes de costos/impuestos y utilidad objetivo.
A6: Cambiar aquí una tarifa actualiza automáticamente la matriz de precios y el cotizador.
A8: 3) Hoja 'Detalle30': actividades de implantación hasta 30 usuarios. Puede editar horas; las hojas 'Horas' y
A9: 'MatrizPrecios' se recalculan. La clasificación presencial/online aplicada es:
A10: Presencial = comité, presentación, levantamiento, certificación y capacitaciones.
A11: Online = configuración, migración, cambios y mantenimiento.
A13: 4) Hoja 'Horas': horas por tramo (30/50/100/150 usuarios) y alcance. Para tramos >30 la normativa solo da totales.
A15: 5) Hoja 'MatrizPrecios': precio de cada combinación tramo × alcance × zona, recalculado con las tarifas vigentes.
A16: El precio de Centroccidental / A4 / 30 usuarios sale corregido (51.760,00) frente al error del documento (58.221,00).
A18: 6) Hoja 'Cotizador': seleccione Zona y Tramo, marque con 'Sí' los alcances a incluir y obtenga el precio,
... A31: 10) Indexación: actualice el índice de inflación (Parámetros!B25) mensualmente según BCV y multiplíquelo por los precios.
